{
  "name": "policy-Twitter-MongoDb",
  "sparkStreamingWindow": 6000,
  "rawData": {
    "enabled": "false",
    "partitionFormat": "day",
    "path": "myTestParquetPath"
  },
  "checkpointing": {
    "path": "checkpoint",
    "timeDimension": "minute",
    "granularity": "minute",
    "interval": 30000,
    "timeAvailability": 60000
  },
  "inputs": [
    {
      "name": "in-twitter",
      "type": "Twitter",
      "configuration": {
        "consumerKey": "****",
        "consumerSecret": "****",
        "accessToken": "****",
        "accessTokenSecret": "****",
        "termsOfSearch": "#hekj,prlk,#drm"
      }
    }
  ],
  "cubes": [
    {
      "name": "testCube",
      "dimensions": [
        {
          "field": "status",
          "name": "hashtags",
          "type": "TwitterStatus",
          "precision": "hashtags"
        },
        {
          "field": "status",
          "name": "firsthashtag",
          "type": "TwitterStatus",
          "precision": "firsthashtag"
        },
        {
          "field": "status",
          "name": "retweets",
          "type": "TwitterStatus",
          "precision": "retweets"
        },
        {
          "name": "userLocation",
          "field": "userLocation"
        },
        {
          "field": "geolocation",
          "name": "precision3",
          "type": "GeoHash",
          "precision": "precision3"
        },
        {
          "field": "timestamp",
          "name": "minute",
          "type": "DateTime",
          "precision": "minute"
        }
      ],
      "operators": [
        {
          "name": "count-operator",
          "type": "Count",
          "configuration": {}
        },
        {
          "name": "sum-operator",
          "type": "Sum",
          "configuration": {
            "inputField": "wordsN"
          }
        },
        {
          "name": "max-operator",
          "type": "Max",
          "configuration": {
            "inputField": "wordsN"
          }
        },
        {
          "name": "min-operator",
          "type": "Min",
          "configuration": {
            "inputField": "wordsN"
          }
        },
        {
          "name": "avg-operator",
          "type": "Avg",
          "configuration": {
            "inputField": "wordsN"
          }
        },
        {
          "name": "median-operator",
          "type": "Median",
          "configuration": {
            "inputField": "wordsN"
          }
        },
        {
          "name": "fullText-operator",
          "type": "FullText",
          "configuration": {
            "inputField": "userLocation"
          }
        }
      ]
    }
  ],
  "outputs": [
    {
      "name": "out-mongo",
      "type": "MongoDb",
      "configuration": {
        "clientUri": "mongodb://localhost:27017",
        "dbName": "sparkta"
      }
    }
  ]
}